README.md
setup.py
boardify/__init__.py
boardify/dashboard.py
boardify/server.py
boardify.egg-info/PKG-INFO
boardify.egg-info/SOURCES.txt
boardify.egg-info/dependency_links.txt
boardify.egg-info/requires.txt
boardify.egg-info/top_level.txt
boardify/blocks/__init__.py
boardify/blocks/bar.py
boardify/blocks/block.py
boardify/blocks/line.py
boardify/blocks/table.py