Metadata-Version: 2.1
Name: boardify
Version: 0.5.1
Summary: A web-based dashboard to analyzing your data with Python
Home-page: https://github.com/Lanseuo/boardify
Author: Lucas Hild
Author-email: contact@lucas-hild.de
License: MIT
Platform: UNKNOWN
